praktipy/__init__.py
praktipy/__version__.py
praktipy/matplotlib_header.tex
praktipy/matplotlib_header_minimal.tex
praktipy/praktiplot.py
praktipy/praktipy.mplstyle
praktipy/tablehandler.py
praktipy/tabletool.py
praktipy/legacy/__init__.py
praktipy/legacy/matplotlib_header.tex
praktipy/legacy/praktiplot.py
praktipy/legacy/tablehandler.py
praktipy/legacy/tabletool.py
praktipy-2.1.11.dist-info/LICENSE
praktipy-2.1.11.dist-info/METADATA
praktipy-2.1.11.dist-info/WHEEL
praktipy-2.1.11.dist-info/top_level.txt
praktipy-2.1.11.dist-info/RECORD
