Metadata-Version: 2.1
Name: praktipy
Version: 2.1.11
Summary: A small toolbox for physics laboratory courses at the TU Dortmund.
Home-page: https://github.com/The-Ludwig/praktipy
Author: Ludwig Neste <The-Ludwig>, Max Uetrecht <phenomax>
License: MIT
Platform: UNKNOWN
Classifier: License :: OSI Approved :: MIT License
Classifier: Programming Language :: Python
Classifier: Programming Language :: Python :: 3
Classifier: Programming Language :: Python :: 3.6
Classifier: Programming Language :: Python :: 3.7
Classifier: Intended Audience :: Developers
Classifier: Intended Audience :: Science/Research
Classifier: Natural Language :: English
Classifier: Natural Language :: German
Classifier: Operating System :: OS Independent
Classifier: Operating System :: Microsoft :: Windows
Classifier: Operating System :: Unix
Classifier: Topic :: Scientific/Engineering :: Physics
Classifier: Topic :: Scientific/Engineering :: Visualization
Classifier: Topic :: Education
Requires-Python: >=3.6.0
Requires-Dist: matplotlib
Requires-Dist: uncertainties
Requires-Dist: numpy
Requires-Dist: pint
Requires-Dist: scipy
Provides-Extra: dev
Requires-Dist: twine ; extra == 'dev'
